pythutils/__init__.py
pythutils/__version__.py
pythutils/datutils.py
pythutils/drawutils.py
pythutils/fileutils.py
pythutils/mathutils.py
pythutils/mediautils.py
pythutils/sysutils.py
pythutils/timeutils.py
pythutils-1.3.21.dist-info/LICENSE
pythutils-1.3.21.dist-info/METADATA
pythutils-1.3.21.dist-info/WHEEL
pythutils-1.3.21.dist-info/top_level.txt
pythutils-1.3.21.dist-info/RECORD
