Metadata-Version: 2.2
Name: pythutils
Version: 1.3.21
Summary: pythutils: a collection of utility functions for Python
Home-page: https://github.com/JolleJolles
Download-URL: https://github.com/JolleJolles/pythutils/archive/1.3.15.tar.gz
Author: Jolle Jolles
Author-email: j.w.jolles@gmail.com
Maintainer: Jolle Jolles
Maintainer-email: j.w.jolles@gmail.com
License: License :: OSI Approved :: Apache Software License
Platform: Windows
Platform: Linux
Platform: Mac OS-X
Classifier: Intended Audience :: Science/Research
Classifier: Programming Language :: Python :: 2.7
Classifier: Programming Language :: Python :: 3
Classifier: License :: OSI Approved :: Apache Software License
Classifier: Topic :: Scientific/Engineering :: Visualization
Classifier: Topic :: Scientific/Engineering :: Image Recognition
Classifier: Topic :: Scientific/Engineering :: Information Analysis
Classifier: Topic :: Multimedia :: Video
Classifier: Operating System :: POSIX
Classifier: Operating System :: Unix
Classifier: Operating System :: MacOS
License-File: LICENSE
Requires-Dist: numpy==1.16.5; python_version >= "2" and python_version < "3"
Requires-Dist: numpy; python_version >= "3"
Requires-Dist: pyyaml
Requires-Dist: objsize
Requires-Dist: seaborn
Dynamic: author
Dynamic: author-email
Dynamic: classifier
Dynamic: description
Dynamic: description-content-type
Dynamic: download-url
Dynamic: home-page
Dynamic: license
Dynamic: maintainer
Dynamic: maintainer-email
Dynamic: platform
Dynamic: requires-dist
Dynamic: summary
